cmd2_abbrev/__init__.py
cmd2_abbrev/abbrev.py
cmd2_abbrev-1.1.0.dist-info/LICENSE
cmd2_abbrev-1.1.0.dist-info/METADATA
cmd2_abbrev-1.1.0.dist-info/WHEEL
cmd2_abbrev-1.1.0.dist-info/top_level.txt
cmd2_abbrev-1.1.0.dist-info/RECORD
